titandevice/__init__.py
titandevice/_device_exception.py
titandevice/_device_manager.py
titandevice/_device_models.py
titandevice/_titian_exception.py
titandevice/utils.py
titandevice/android/__init__.py
titandevice/android/_device.py
titandevice/android/_frida.py
titandevice/android/_frida_manager.py
titandevice/android/_package_manager.py
titandevice/android/device.py
titandevice/android/device_manager.py
titandevice/android/frida.py
titandevice/android/frida_manager.py
titandevice/android/package_manager.py
titandevice/android/application/__init__.py
titandevice/android/application/application.py
titandevice/android/application/package.py
titandevice/android/application/package_manager.py
titandevice/android/application/test.py
titandevice/android/capture/__init__.py
titandevice/android/capture/capture_manager.py
titandevice/android/config/__init__.py
titandevice/android/device/__init__.py
titandevice/android/device/device_manager.py
titandevice/android/frida/__init__.py
titandevice/android/frida/frida_app.py
titandevice/android/frida/frida_app_manager.py
titandevice/android/frida/frida_device.py
titandevice/android/frida/frida_device_manager.py
titandevice/exception/__init__.py
titandevice/utils/__init__.py
titandevice/utils/adb_utils.py
titandevice/utils/logger_utils.py
titandevice-0.5.0.dist-info/METADATA
titandevice-0.5.0.dist-info/WHEEL
titandevice-0.5.0.dist-info/top_level.txt
titandevice-0.5.0.dist-info/RECORD
