Metadata-Version: 2.1
Name: titandevice
Version: 0.5.0
Summary: A Python library used for managing device
Author: 369
Author-email: luck.yangbo@gmai.com
Classifier: Programming Language :: Python :: 3
Classifier: License :: OSI Approved :: MIT License
Classifier: Operating System :: OS Independent
Requires-Python: >=3.6
Requires-Dist: adbutils
Requires-Dist: pydantic
